README
setup.py
chtMultiRegionSimpleFlux/__init__.py
chtMultiRegionSimpleFlux.egg-info/PKG-INFO
chtMultiRegionSimpleFlux.egg-info/SOURCES.txt
chtMultiRegionSimpleFlux.egg-info/dependency_links.txt
chtMultiRegionSimpleFlux.egg-info/entry_points.txt
chtMultiRegionSimpleFlux.egg-info/requires.txt
chtMultiRegionSimpleFlux.egg-info/top_level.txt
chtMultiRegionSimpleFlux.egg-info/zip-safe
chtMultiRegionSimpleFlux/r2_1_1/__init__.py
chtMultiRegionSimpleFlux/r2_1_1/fluid/__init__.py
chtMultiRegionSimpleFlux/r2_1_1/solid/__init__.py